CHANGELOG.md
pickle_compat/__init__.py
pickle_compat/compat.py
pickle_compat/examples.py
pickle_compat-2.1.1.dist-info/LICENSE
pickle_compat-2.1.1.dist-info/WHEEL
pickle_compat-2.1.1.dist-info/METADATA
pickle_compat-2.1.1.dist-info/RECORD
