Metadata-Version: 2.1
Name: pickle-compat
Version: 2.1.1
Summary: Python 2/3 compatibility layer for Pickle
Home-page: https://github.com/imankulov/pickle-compat
License: MIT
Author: Doist Developers
Author-email: dev@doist.com
Requires-Python: >=2.7, !=3.0.*, !=3.1.*, !=3.2.*, !=3.3.*, !=3.4.*, !=3.5.*, !=3.6.*
Classifier: Intended Audience :: Developers
Classifier: License :: OSI Approved :: MIT License
Classifier: Programming Language :: Python :: 2
Classifier: Programming Language :: Python :: 2.7
Classifier: Programming Language :: Python :: 3
Classifier: Programming Language :: Python :: 3.10
Classifier: Programming Language :: Python :: 3.7
Classifier: Programming Language :: Python :: 3.8
Classifier: Programming Language :: Python :: 3.9
Project-URL: Repository, https://github.com/imankulov/pickle-compat
